mpl_qtthread/__init__.py
mpl_qtthread/_version.py
mpl_qtthread/backend.py
mpl_qtthread/backend_agg.py
mpl_qtthread/tests/__init__.py
mpl_qtthread/tests/conftest.py
mpl_qtthread/tests/test_examples.py
mpl_qtthread-0.0.1.dist-info/AUTHORS.rst
mpl_qtthread-0.0.1.dist-info/LICENSE
mpl_qtthread-0.0.1.dist-info/METADATA
mpl_qtthread-0.0.1.dist-info/WHEEL
mpl_qtthread-0.0.1.dist-info/entry_points.txt
mpl_qtthread-0.0.1.dist-info/top_level.txt
mpl_qtthread-0.0.1.dist-info/RECORD
