Metadata-Version: 2.1
Name: mpl-qtthread
Version: 0.0.1
Summary: A Matplotlib backend for working with (Q)Threads and Qt
Home-page: https://github.com/tacaswell/mpl-qtthread
Author: Brookhaven National Laboratory
Author-email: tcaswell@bnl.gov
License: BSD (3-clause)
Platform: UNKNOWN
Classifier: Development Status :: 2 - Pre-Alpha
Classifier: Natural Language :: English
Classifier: Programming Language :: Python :: 3
Requires-Python: >=3.7
License-File: LICENSE
License-File: AUTHORS.rst
Requires-Dist: matplotlib
Requires-Dist: pyqt5
